ambient_base_plugin/__init__.py
ambient_base_plugin/base_plugin.py
ambient_base_plugin/models/__init__.py
ambient_base_plugin/models/configuration.py
ambient_base_plugin/models/exceptions.py
ambient_base_plugin/models/message.py
ambient_base_plugin-1.8.0.dist-info/METADATA
ambient_base_plugin-1.8.0.dist-info/WHEEL
ambient_base_plugin-1.8.0.dist-info/top_level.txt
ambient_base_plugin-1.8.0.dist-info/RECORD
