Metadata-Version: 2.4
Name: ambient-base-plugin
Version: 1.8.0
Summary: An abstract base class for Ambient platform plugins.
Author-email: Jose Catarino <jose@ambientlabscomputing.com>
License: MIT
Keywords: ambient,plugin,abstract base class,plugin interface
Classifier: Development Status :: 3 - Alpha
Classifier: Intended Audience :: Developers
Classifier: Topic :: Software Development :: Libraries :: Application Frameworks
Classifier: Programming Language :: Python :: 3
Classifier: Programming Language :: Python :: 3.7
Classifier: License :: OSI Approved :: MIT License
Classifier: Operating System :: OS Independent
Requires-Python: >=3.7
Requires-Dist: pydantic<=2.7.4
Requires-Dist: ambient_backend_api_client>=3.0.1
Requires-Dist: loguru>=0.7.2
Requires-Dist: apluggy>=1.0.3
